pslmw_md_toc/__init__.py
pslmw_md_toc/logger_config.py
pslmw_md_toc/pslmw_md_toc.py
pslmw_md_toc-1.0.2.dist-info/licenses/LICENSE
pslmw_md_toc-1.0.2.dist-info/METADATA
pslmw_md_toc-1.0.2.dist-info/WHEEL
pslmw_md_toc-1.0.2.dist-info/top_level.txt
pslmw_md_toc-1.0.2.dist-info/RECORD
