Metadata-Version: 2.4
Name: pslmw-md-toc
Version: 1.0.2
Summary: pslmw-md-toc is a python tool for creating a Table of Contents `TOC` from a directory with a simple execution
Author-email: Emili Garriga Coll <porsilasmocasweb@gmail.com>
Maintainer-email: Emili Garriga Coll <porsilasmocasweb@gmail.com>
License: The MIT License (MIT)
Project-URL: Repository, https://github.com/porsilasmoscasweb/pslmw-md-toc
Project-URL: Bug Tracker, https://github.com/porsilasmoscasweb/pslmw-md-toc/issues
Keywords: markdown,sort,organization,TOC,md,index,files
Classifier: Development Status :: 5 - Production/Stable
Classifier: Programming Language :: Python :: 3
Requires-Python: >=3.9
License-File: LICENSE
Requires-Dist: unidecode
Provides-Extra: test
Requires-Dist: pytest; extra == "test"
Dynamic: license-file
